{
  "employee": [
    {
      "id": 1,
      "name": "Juan",
      "creationDate": "Wed, 07 Dec 2022 02:51:01 GMT",
      "sectors": [
        "Agriculture",
        "Production",
        "Commerce"
      ],
      "holidays": "Available"
    },
    {
      "id": 2,
      "name": "Pedro",
      "creationDate": "Wed, 07 Dec 2022 02:51:41 GMT",
      "sectors": [
        "Construction",
        "Mining",
        "Transport"
      ],
      "holidays": "Pending"
    },
    {
      "id": 3,
      "name": "Carlos",
      "creationDate": "Wed, 07 Dec 2022 03:11:08 GMT",
      "sectors": [
        "Agriculture",
        "Commerce",
        "Mining"
      ],
      "holidays": "Not Available"
    }
  ]
}
